GoYuyanBokeShijian/README.md
GoYuyanBokeShijian/__init__.py
GoYuyanBokeShijian/__main__.py
GoYuyanBokeShijian/file.epub
GoYuyanBokeShijian/index.html
GoYuyanBokeShijian/css/__init__.py
GoYuyanBokeShijian/css/annotations.css
GoYuyanBokeShijian/css/main.css
GoYuyanBokeShijian/css/normalize.css
GoYuyanBokeShijian/css/popup.css
GoYuyanBokeShijian/font/__init__.py
GoYuyanBokeShijian/font/fontello.eot
GoYuyanBokeShijian/font/fontello.svg
GoYuyanBokeShijian/font/fontello.ttf
GoYuyanBokeShijian/font/fontello.woff
GoYuyanBokeShijian/img/__init__.py
GoYuyanBokeShijian/img/annotator-glyph-sprite.png
GoYuyanBokeShijian/img/annotator-icon-sprite.png
GoYuyanBokeShijian/img/apple-touch-icon.png
GoYuyanBokeShijian/img/cancelfullscreen.png
GoYuyanBokeShijian/img/close.png
GoYuyanBokeShijian/img/fullscreen.png
GoYuyanBokeShijian/img/loader.gif
GoYuyanBokeShijian/img/menu-icon.png
GoYuyanBokeShijian/img/save.png
GoYuyanBokeShijian/img/saved.png
GoYuyanBokeShijian/img/settings-s.png
GoYuyanBokeShijian/img/settings.png
GoYuyanBokeShijian/img/star.png
GoYuyanBokeShijian/js/__init__.py
GoYuyanBokeShijian/js/epub.js
GoYuyanBokeShijian/js/epub.min.js
GoYuyanBokeShijian/js/epub.min.map
GoYuyanBokeShijian/js/hooks.min.js
GoYuyanBokeShijian/js/hooks.min.map
GoYuyanBokeShijian/js/reader.js
GoYuyanBokeShijian/js/reader.js.map
GoYuyanBokeShijian/js/reader.min.js
GoYuyanBokeShijian/js/reader.min.map
GoYuyanBokeShijian/js/hooks/__init__.py
GoYuyanBokeShijian/js/hooks/extensions/__init__.py
GoYuyanBokeShijian/js/hooks/extensions/highlight.js
GoYuyanBokeShijian/js/libs/__init__.py
GoYuyanBokeShijian/js/libs/jquery.min.js
GoYuyanBokeShijian/js/libs/localforage.min.js
GoYuyanBokeShijian/js/libs/screenfull.js
GoYuyanBokeShijian/js/libs/screenfull.min.js
GoYuyanBokeShijian/js/libs/zip.min.js
GoYuyanBokeShijian/js/plugins/__init__.py
GoYuyanBokeShijian/js/plugins/hypothesis.js
GoYuyanBokeShijian/js/plugins/search.js
go_yuyan_boke_shijian-2024.3.1.0.dist-info/METADATA
go_yuyan_boke_shijian-2024.3.1.0.dist-info/WHEEL
go_yuyan_boke_shijian-2024.3.1.0.dist-info/entry_points.txt
go_yuyan_boke_shijian-2024.3.1.0.dist-info/top_level.txt
go_yuyan_boke_shijian-2024.3.1.0.dist-info/RECORD
